{"modulePrefix":"client1","podModulePrefix":"client1/pods","environment":"development","baseURL":"/","locationType":"auto","EmberENV":{"FEATURES":{}},"APP":{"LOG_RESOLVER":true,"LOG_ACTIVE_GENERATION":true,"LOG_TRANSITIONS":true,"LOG_TRANSITIONS_INTERNAL":true,"LOG_VIEW_LOOKUPS":true,"name":"client1","version":"0.0.0+dad44907"},"contentSecurityPolicy":{"default-src":"'none'","script-src":"'self'","font-src":"'self' 'unsafe-eval' https://fonts.gstatic.com","connect-src":"'self' 'unsafe-eval' http://rest-test-csepelbicikli.c9users.io","img-src":"'self'","style-src":"'self' 'unsafe-eval' https://fonts.googleapis.com","media-src":"'self'"},"contentSecurityPolicyHeader":"Content-Security-Policy-Report-Only","exportApplicationGlobal":true}